elarian/__init__.py
elarian/client.py
elarian/customer.py
elarian/elarian.py
elarian/simulator.py
elarian/models/__init__.py
elarian/utils/__init__.py
elarian/utils/helpers.py
elarian/utils/request_handler.py
elarian/utils/generated/__init__.py
elarian/utils/generated/activity_model_pb2.py
elarian/utils/generated/activity_state_pb2.py
elarian/utils/generated/app_model_pb2.py
elarian/utils/generated/app_socket_pb2.py
elarian/utils/generated/app_state_pb2.py
elarian/utils/generated/common_model_pb2.py
elarian/utils/generated/identity_state_pb2.py
elarian/utils/generated/messaging_model_pb2.py
elarian/utils/generated/messaging_state_pb2.py
elarian/utils/generated/payment_model_pb2.py
elarian/utils/generated/payment_state_pb2.py
elarian/utils/generated/simulator_socket_pb2.py
reactivestreams/__init__.py
reactivestreams/publisher.py
reactivestreams/subscriber.py
reactivestreams/subscription.py
rsocket/__init__.py
rsocket/composite_metadata.py
rsocket/connection.py
rsocket/frame.py
rsocket/handlers.py
rsocket/payload.py
rsocket/rsocket.py
rsocket/timer.py
rsocket/wellknown_mimetype.py
elarian-0.0.8.dist-info/LICENSE
elarian-0.0.8.dist-info/METADATA
elarian-0.0.8.dist-info/WHEEL
elarian-0.0.8.dist-info/top_level.txt
elarian-0.0.8.dist-info/RECORD
