Metadata-Version: 2.1
Name: elarian
Version: 0.0.8
Summary: Official Elarian Python SDK
Home-page: https://github.com/ElarianLtd/python-sdk
Author: Elarian
Author-email: sbalekage@elarian.com
License: MIT
Keywords: elarian africastalking sms ussd voice customer payments
Platform: UNKNOWN
Classifier: License :: OSI Approved :: MIT License
Classifier: Programming Language :: Python :: 3
Classifier: Programming Language :: Python :: 3.7
Classifier: Programming Language :: Python :: 3.9
Requires-Python: >=3.7
License-File: LICENSE
